cosmos_predict2/__init__.py
cosmos_predict2/checkpointer.py
cosmos_predict2/conditioner.py
cosmos_predict2/auxiliary/__init__.py
cosmos_predict2/auxiliary/cosmos_reason1.py
cosmos_predict2/auxiliary/guardrail/__init__.py
cosmos_predict2/auxiliary/guardrail/blocklist/__init__.py
cosmos_predict2/auxiliary/guardrail/blocklist/blocklist.py
cosmos_predict2/auxiliary/guardrail/blocklist/utils.py
cosmos_predict2/auxiliary/guardrail/common/__init__.py
cosmos_predict2/auxiliary/guardrail/common/core.py
cosmos_predict2/auxiliary/guardrail/common/io_utils.py
cosmos_predict2/auxiliary/guardrail/common/presets.py
cosmos_predict2/auxiliary/guardrail/face_blur_filter/__init__.py
cosmos_predict2/auxiliary/guardrail/face_blur_filter/blur_utils.py
cosmos_predict2/auxiliary/guardrail/face_blur_filter/face_blur_filter.py
cosmos_predict2/auxiliary/guardrail/face_blur_filter/retinaface_utils.py
cosmos_predict2/auxiliary/guardrail/llamaGuard3/__init__.py
cosmos_predict2/auxiliary/guardrail/llamaGuard3/categories.py
cosmos_predict2/auxiliary/guardrail/llamaGuard3/llamaGuard3.py
cosmos_predict2/auxiliary/guardrail/video_content_safety_filter/__init__.py
cosmos_predict2/auxiliary/guardrail/video_content_safety_filter/model.py
cosmos_predict2/auxiliary/guardrail/video_content_safety_filter/video_content_safety_filter.py
cosmos_predict2/auxiliary/guardrail/video_content_safety_filter/vision_encoder.py
cosmos_predict2/callbacks/__init__.py
cosmos_predict2/callbacks/device_monitor.py
cosmos_predict2/callbacks/every_n_draw_sample.py
cosmos_predict2/callbacks/every_n_draw_sample_multiviewvideo.py
cosmos_predict2/callbacks/grad_clip.py
cosmos_predict2/callbacks/iter_speed.py
cosmos_predict2/callbacks/loss_log.py
cosmos_predict2/configs/__init__.py
cosmos_predict2/configs/conditioner.py
cosmos_predict2/configs/action_conditioned/__init__.py
cosmos_predict2/configs/action_conditioned/config.py
cosmos_predict2/configs/action_conditioned/defaults/__init__.py
cosmos_predict2-1.0.8.dist-info/METADATA
cosmos_predict2-1.0.8.dist-info/WHEEL
cosmos_predict2-1.0.8.dist-info/licenses/LICENSE
cosmos_predict2-1.0.8.dist-info/RECORD
